xync_scripts/__init__.py
xync_scripts/cycle.py
xync_scripts/earns_upd.py
xync_scripts/init.py
xync_scripts/loader.py
xync_scripts/utils.py
xync_scripts-0.2.5.dist-info/METADATA
xync_scripts-0.2.5.dist-info/WHEEL
xync_scripts-0.2.5.dist-info/top_level.txt
xync_scripts-0.2.5.dist-info/RECORD
